vevor_heater_ble/__init__.py
vevor_heater_ble/const.py
vevor_heater_ble/heater.py
vevor_heater_ble/setup.py
vevor_heater_ble-0.1.3.dist-info/LICENSE
vevor_heater_ble-0.1.3.dist-info/METADATA
vevor_heater_ble-0.1.3.dist-info/WHEEL
vevor_heater_ble-0.1.3.dist-info/top_level.txt
vevor_heater_ble-0.1.3.dist-info/RECORD
