Metadata-Version: 2.1
Name: vevor-heater-ble
Version: 0.1.3
Summary: A simple API for BLE-enabled Vevor independent heaters
Author-email: iotmaestro@proton.me
License: MIT License
Project-URL: Repository, https://github.com/iotmaestro/vevor-heater-ble
Classifier: Development Status :: 4 - Beta
Classifier: Programming Language :: Python :: 3
Requires-Python: >=3.6
License-File: LICENSE
Requires-Dist: bleak >=0.21.1
Requires-Dist: bleak-retry-connector >=3.2.1
